<list>
  <rule>
    <premise>
      <Name>Flower</Name>
    </premise>
    <conclusion>
      <Name>Joy</Name>
    </conclusion>
  </rule>
<rule>
    <premise>
      <Name>Restaurant</Name>
    </premise>
    <conclusion>
      <Name>Eat</Name>
    </conclusion>
  </rule>
  <rule>
    <premise>
      <Name>Restaurant</Name>
    </premise>
    <conclusion>
      <Name>Joy</Name>
    </conclusion>
  </rule>
    <rule>
    <premise>
      <Name>Eat</Name>
    </premise>
    <conclusion>
      <Name>Joy</Name>
    </conclusion>
  </rule>
  <rule>
    <premise>
      <Name>Flower</Name>
    </premise>
    <conclusion>
      <Name>Angry</Name>
    </conclusion>
  </rule>
    <rule>
    <premise>
      <Name>Chaussette</Name>
    </premise>
    <conclusion>
      <Name>Trou</Name>
    </conclusion>
  </rule>
  <rule>
    <premise>
      <Name>Beauty</Name>
    </premise>
    <conclusion>
      <Name>Joy</Name>
    </conclusion>
  </rule>
  <rule>
    <premise>
      <Name>Dog</Name>
    </premise>
    <conclusion>
      <Name>Nice</Name>
    </conclusion>
  </rule>
   <rule>
    <premise>
      <Name>Flower</Name>
    </premise>
    <conclusion>
      <Name>Beauty</Name>
	</conclusion>
  </rule>
  <rule>
    <premise>
      <Name>Dog</Name>
    </premise>
    <conclusion>
      <Name>Dangerous</Name>
    </conclusion>
  </rule>
  <rule>
    <premise>
      <Name>Freind</Name>
    </premise>
    <conclusion>
      <Name>Trust</Name>
    </conclusion>
  </rule>
  <rule>
    <premise>
      <Name>Trust</Name>
    </premise>
    <conclusion>
      <Name>Good</Name>
    </conclusion>
  </rule>
  <rule>
    <premise>
      <Name>Dog</Name>
    </premise>
    <conclusion>
      <Name>Freind</Name>
    </conclusion>
  </rule>
  <rule>
    <premise>
      <Name>Snake</Name>
    </premise>
    <conclusion>
      <Name>Dangerous</Name>
    </conclusion>
  </rule>
  <rule>
    <premise>
      <Name>Beauty</Name>
    </premise>
    <conclusion>
      <Name>Good</Name>
    </conclusion>
  </rule>
  <rule>
    <premise>
      <Name>Car</Name>
    </premise>
    <conclusion>
      <Name>Danger</Name>
    </conclusion>
  </rule>
  <rule>
    <premise>
      <Name>Car</Name>
    </premise>
    <conclusion>
      <Name>Fear</Name>
    </conclusion>
  </rule>
  <rule>
    <premise>
      <Name>Danger</Name>
    </premise>
    <conclusion>
      <Name>Fear</Name>
    </conclusion>
  </rule>
  <rule>
    <premise>
      <Name>Car</Name>
    </premise>
    <conclusion>
      <Name>Speed</Name>
    </conclusion>
  </rule>
  <rule>
    <premise>
      <Name>Speed</Name>
    </premise>
    <conclusion>
      <Name>Dangerous</Name>
    </conclusion>
  </rule>
  <rule>
    <premise>
      <Name>Building</Name>
    </premise>
    <conclusion>
      <Name>Work</Name>
    </conclusion>
  </rule>
  <!-- <rule>
    <premise>
      <Name>Work</Name>
    </premise>
    <conclusion>
      <Name>Sadness</Name>
    </conclusion>
  </rule>  -->
  <rule>
    <premise>
      <Name>Building</Name>
    </premise>
    <conclusion>
      <Name>Croud</Name>
    </conclusion>
  </rule>
  <rule>
    <premise>
      <Name>Croud</Name>
    </premise>
    <conclusion>
      <Name>Disgust</Name>
    </conclusion>
  </rule>
  <rule>
    <premise>
      <Name>Bus</Name>
    </premise>
    <conclusion>
      <Name>Croud</Name>
    </conclusion>
  </rule>
  <rule>
    <premise>
      <Name>High_sound</Name>
    </premise>
    <conclusion>
      <Name>Surprise</Name>
    </conclusion>
  </rule>
  <rule>
    <premise>
      <Name>unfair</Name>
    </premise>
    <conclusion>
      <Name>Angry</Name>
    </conclusion>
  </rule>
  
  

  
</list>